pytest_solr/__init__.py
pytest_solr/factories.py
pytest_solr/plugin.py
pytest_solr-1.0.0.dist-info/METADATA
pytest_solr-1.0.0.dist-info/WHEEL
pytest_solr-1.0.0.dist-info/entry_points.txt
pytest_solr-1.0.0.dist-info/top_level.txt
pytest_solr-1.0.0.dist-info/RECORD
