Metadata-Version: 2.1
Name: pytest-solr
Version: 1.0.0
Summary: Solr process and client fixtures for py.test.
Home-page: https://github.com/kitconcept/pytest-solr
Author: kitconcept GmbH
Author-email: info@kitconcept.com
License: MIT
Keywords: tests py.test pytest fixture solr
Platform: UNKNOWN
Classifier: Development Status :: 3 - Alpha
Classifier: Intended Audience :: Developers
Classifier: License :: OSI Approved :: MIT License
Classifier: Operating System :: OS Independent
Classifier: Topic :: Software Development :: Testing
Classifier: Topic :: Software Development :: Libraries
Classifier: Topic :: Utilities
Classifier: Programming Language :: Python
Classifier: Programming Language :: Python :: 2
Classifier: Programming Language :: Python :: 2.7
Classifier: Programming Language :: Python :: 3
Classifier: Programming Language :: Python :: 3.6
Requires-Dist: pytest (>=3.0.0)
Requires-Dist: pysolr
